{
  "@context": "http://iiif.io/api/image/3/context.json",
  "id": "https://iiif.tiju.ca/tjrj_02_267_597_8/5a0eb742ef25be895d0a471595a157f4",
  "type": "ImageService3",
  "profile": "level0",
  "protocol": "http://iiif.io/api/image",
  "tiles": [
    {
      "scaleFactors": [
        1,
        2,
        4,
        8
      ],
      "width": 256
    }
  ],
  "width": 2005,
  "height": 3224,
  "sizes": [
    {
      "width": 186,
      "height": 300
    },
    {
      "width": 1244,
      "height": 2000
    }
  ]
}