{
  "@context": "http://iiif.io/api/image/3/context.json",
  "id": "https://iiif.tiju.ca/ny00459516/5c2d5b34b5ea9e59dca3d31a4833db6b",
  "type": "ImageService3",
  "profile": "level0",
  "protocol": "http://iiif.io/api/image",
  "tiles": [
    {
      "scaleFactors": [
        1,
        2,
        4,
        8,
        16
      ],
      "width": 256
    }
  ],
  "width": 4900,
  "height": 7250,
  "sizes": [
    {
      "width": 203,
      "height": 300
    },
    {
      "width": 1352,
      "height": 2000
    }
  ]
}