{
  "@context": "http://iiif.io/api/image/3/context.json",
  "id": "https://iiif.tiju.ca/858588407x/2b404877ff126831c424ba773499e088",
  "type": "ImageService3",
  "profile": "level0",
  "protocol": "http://iiif.io/api/image",
  "tiles": [
    {
      "scaleFactors": [
        1,
        2,
        4
      ],
      "width": 256
    }
  ],
  "width": 1404,
  "height": 1985,
  "sizes": [
    {
      "width": 212,
      "height": 300
    },
    {
      "width": 1404,
      "height": 1985
    }
  ]
}