{
  "@context": "http://iiif.io/api/image/3/context.json",
  "id": "https://iiif.tiju.ca/us01346768/59a2ff6bc88a3c1e75b050167b02d5df",
  "type": "ImageService3",
  "profile": "level0",
  "protocol": "http://iiif.io/api/image",
  "tiles": [
    {
      "scaleFactors": [
        1,
        2,
        4,
        8,
        16
      ],
      "width": 256
    }
  ],
  "width": 3744,
  "height": 5616,
  "sizes": [
    {
      "width": 200,
      "height": 300
    },
    {
      "width": 1333,
      "height": 2000
    }
  ]
}