{
  "@context": "http://iiif.io/api/image/3/context.json",
  "id": "https://iiif.tiju.ca/bnbr_drg605826/f128e409f6c695d24cbc0223f93ae850",
  "type": "ImageService3",
  "profile": "level0",
  "protocol": "http://iiif.io/api/image",
  "tiles": [
    {
      "scaleFactors": [
        1,
        2,
        4,
        8
      ],
      "width": 256
    }
  ],
  "width": 1964,
  "height": 2433,
  "sizes": [
    {
      "width": 242,
      "height": 300
    },
    {
      "width": 1614,
      "height": 2000
    }
  ]
}