{
  "@context": "http://iiif.io/api/image/3/context.json",
  "id": "https://iiif.tiju.ca/p06701369/6e8049cb9230c82305d733acebc29133",
  "type": "ImageService3",
  "profile": "level0",
  "protocol": "http://iiif.io/api/image",
  "tiles": [
    {
      "scaleFactors": [
        1,
        2,
        4,
        8,
        16
      ],
      "width": 256
    }
  ],
  "width": 3327,
  "height": 5142,
  "sizes": [
    {
      "width": 194,
      "height": 300
    },
    {
      "width": 1294,
      "height": 2000
    }
  ]
}