{
  "@context": "http://iiif.io/api/image/3/context.json",
  "id": "https://iiif.tiju.ca/ccnft1966/700e702d923c1b89924d7ef78adfbdac",
  "type": "ImageService3",
  "profile": "level0",
  "protocol": "http://iiif.io/api/image",
  "tiles": [
    {
      "scaleFactors": [
        1,
        2,
        4
      ],
      "width": 256
    }
  ],
  "width": 1341,
  "height": 1950,
  "sizes": [
    {
      "width": 206,
      "height": 300
    },
    {
      "width": 1341,
      "height": 1950
    }
  ]
}