{
  "@context": "http://iiif.io/api/image/3/context.json",
  "id": "https://iiif.tiju.ca/ccnft1966/dac4d9d946769f166519cd7eb1c947cb",
  "type": "ImageService3",
  "profile": "level0",
  "protocol": "http://iiif.io/api/image",
  "tiles": [
    {
      "scaleFactors": [
        1,
        2,
        4,
        8
      ],
      "width": 256
    }
  ],
  "width": 1416,
  "height": 2153,
  "sizes": [
    {
      "width": 197,
      "height": 300
    },
    {
      "width": 1315,
      "height": 2000
    }
  ]
}