{
  "@context": "http://iiif.io/api/image/3/context.json",
  "id": "https://iiif.tiju.ca/858588407x/6d69da9a68e767832c2d69ce0f1a7698",
  "type": "ImageService3",
  "profile": "level0",
  "protocol": "http://iiif.io/api/image",
  "tiles": [
    {
      "scaleFactors": [
        1,
        2,
        4
      ],
      "width": 256
    }
  ],
  "width": 1351,
  "height": 1996,
  "sizes": [
    {
      "width": 203,
      "height": 300
    },
    {
      "width": 1351,
      "height": 1996
    }
  ]
}