{
  "@context": "http://iiif.io/api/image/3/context.json",
  "id": "https://iiif.tiju.ca/ccnft1966/d425a741febbdd2ae3952b7c145b3642",
  "type": "ImageService3",
  "profile": "level0",
  "protocol": "http://iiif.io/api/image",
  "tiles": [
    {
      "scaleFactors": [
        1,
        2,
        4
      ],
      "width": 256
    }
  ],
  "width": 1369,
  "height": 1993,
  "sizes": [
    {
      "width": 206,
      "height": 300
    },
    {
      "width": 1369,
      "height": 1993
    }
  ]
}