{
  "@context": "http://iiif.io/api/image/3/context.json",
  "id": "https://iiif.tiju.ca/tjrj_02_267_597_8/341632fdfd5d67e7bb6d9d4d5947cd6d",
  "type": "ImageService3",
  "profile": "level0",
  "protocol": "http://iiif.io/api/image",
  "tiles": [
    {
      "scaleFactors": [
        1,
        2,
        4,
        8
      ],
      "width": 256
    }
  ],
  "width": 2029,
  "height": 3224,
  "sizes": [
    {
      "width": 188,
      "height": 300
    },
    {
      "width": 1259,
      "height": 2000
    }
  ]
}